LICENSE
README.md
pyproject.toml
src/simapy/__init__.py
src/simapy/progress_handler.py
src/simapy/sima_reader.py
src/simapy/sima_writer.py
src/simapy/sre.py
src/simapy.egg-info/PKG-INFO
src/simapy.egg-info/SOURCES.txt
src/simapy.egg-info/dependency_links.txt
src/simapy.egg-info/requires.txt
src/simapy.egg-info/top_level.txt
src/simapy/metocean/__init__.py
src/simapy/metocean/metocean.py
src/simapy/metocean/package_info.py
src/simapy/metocean/blueprints/__init__.py
src/simapy/metocean/blueprints/metocean.py
src/simapy/metocean/hindcast/__init__.py
src/simapy/metocean/hindcast/hindcast.py
src/simapy/metocean/hindcast/stochasticcurrent.py
src/simapy/metocean/hindcast/stochasticwave.py
src/simapy/metocean/hindcast/stochasticwind.py
src/simapy/metocean/hindcast/blueprints/__init__.py
src/simapy/metocean/hindcast/blueprints/hindcast.py
src/simapy/metocean/hindcast/blueprints/stochasticcurrent.py
src/simapy/metocean/hindcast/blueprints/stochasticwave.py
src/simapy/metocean/hindcast/blueprints/stochasticwind.py
src/simapy/metocean/longTermStatistics/__init__.py
src/simapy/metocean/longTermStatistics/extremevalues.py
src/simapy/metocean/longTermStatistics/hsbinned.py
src/simapy/metocean/longTermStatistics/hsbinnedsector.py
src/simapy/metocean/longTermStatistics/longtermstats.py
src/simapy/metocean/longTermStatistics/period.py
src/simapy/metocean/longTermStatistics/sector.py
src/simapy/metocean/longTermStatistics/weibull.py
src/simapy/metocean/longTermStatistics/blueprints/__init__.py
src/simapy/metocean/longTermStatistics/blueprints/extremevalues.py
src/simapy/metocean/longTermStatistics/blueprints/hsbinned.py
src/simapy/metocean/longTermStatistics/blueprints/hsbinnedsector.py
src/simapy/metocean/longTermStatistics/blueprints/longtermstats.py
src/simapy/metocean/longTermStatistics/blueprints/period.py
src/simapy/metocean/longTermStatistics/blueprints/sector.py
src/simapy/metocean/longTermStatistics/blueprints/weibull.py
src/simapy/metocean/longTermStatistics/level/__init__.py
src/simapy/metocean/longTermStatistics/level/profile.py
src/simapy/metocean/longTermStatistics/level/sectors.py
src/simapy/metocean/longTermStatistics/level/stat.py
