Metadata-Version: 2.4
Name: simapy
Version: 5.0.0
Summary: Python utilities for SIMA
Author: SINTEF Ocean
License: MIT License
Project-URL: Homepage, https://github.com/SINTEF/simapy
Classifier: Programming Language :: Python :: 3
Classifier: License :: OSI Approved :: MIT License
Classifier: Operating System :: OS Independent
Requires-Python: >=3.8
License-File: LICENSE
Requires-Dist: dmtpy==0.3.5
Requires-Dist: numpy
Requires-Dist: tqdm
Dynamic: license-file
